{
    "clients": {
        "Gesn": {
            "version": "0.3.0",
            "platforms": {
                "linux": {
                    "x64": {
                        "download": {
                            "url": "https://gesnstore.blob.core.windows.net/builds/gesn-linux-amd64-0.3.0-6006b0d.tar.gz",
                            "type": "tar",
                            "md5": "be0c69227a322436a0746167570dde47",
                            "bin": "gesn-linux-amd64-0.3.0-6006b0d/gesn"
                        },
                        "bin": "gesn",
                        "commands": {
                            "sanity": {
                                "args": [
                                    "version"
                                ],
                                "output": [
                                    "Gesn",
                                    "0.3.0"
                                ]
                            }
                        }
                    },
                    "ia32": {
                        "download": {
                            "url": "https://gesnstore.blob.core.windows.net/builds/gesn-linux-386-0.3.0-6006b0d.tar.gz",
                            "type": "tar",
                            "md5": "b924c94f301bb1f77a40f130a0d2ff99",
                            "bin": "gesn-linux-386-0.3.0-6006b0d/gesn"
                        },
                        "bin": "gesn",
                        "commands": {
                            "sanity": {
                                "args": [
                                    "version"
                                ],
                                "output": [
                                    "Gesn",
                                    "0.3.0"
                                ]
                            }
                        }
                    }
                },
                "mac": {
                    "x64": {
                        "download": {
                            "url": "https://gesnstore.blob.core.windows.net/builds/gesn-darwin-amd64-0.3.0-6006b0d.tar.gz",
                            "type": "tar",
                            "md5": "452fd4bdb1346b1fce87594612a60c11",
                            "bin": "gesn-darwin-amd64-0.3.0-6006b0d/gesn"
                        },
                        "bin": "gesn",
                        "commands": {
                            "sanity": {
                                "args": [
                                    "version"
                                ],
                                "output": [
                                    "Gesn",
                                    "0.3.0"
                                ]
                            }
                        }
                    }
                },
                "win": {
                    "x64": {
                        "download": {
                            "url": "https://gesnstore.blob.core.windows.net/builds/gesn-windows-amd64-0.3.0-6006b0d.zip",
                            "type": "zip",
                            "md5": "9c360dc6ac763e8209f3c2fddf5ce359",
                            "bin": "gesn-windows-amd64-0.3.0-6006b0d\\gesn.exe"
                        },
                        "bin": "gesn.exe",
                        "commands": {
                            "sanity": {
                                "args": [
                                    "version"
                                ],
                                "output": [
                                    "Gesn",
                                    "0.3.0"
                                ]
                            }
                        }
                    },
                    "ia32": {
                        "download": {
                            "url": "https://gesnstore.blob.core.windows.net/builds/gesn-windows-386-0.3.0-6006b0d.zip",
                            "type": "zip",
                            "md5": "6bfff4b4ee9ce7d9c68849a5f867bce4",
                            "bin": "gesn-windows-386-0.3.0-6006b0d\\gesn.exe"
                        },
                        "bin": "gesn.exe",
                        "commands": {
                            "sanity": {
                                "args": [
                                    "version"
                                ],
                                "output": [
                                    "Gesn",
                                    "0.3.0"
                                ]
                            }
                        }
                    }
                }
            }
        }
    }
}
